line_profiler_extended/__init__.py
line_profiler_extended/ipython_extension.py
line_profiler_extended/lpext.py
line_profiler_extended/py.typed
line_profiler_extended/pytest_plugin.py
line_profiler_extended/utils.py
line_profiler_extended-0.0.3.dist-info/entry_points.txt
line_profiler_extended-0.0.3.dist-info/METADATA
line_profiler_extended-0.0.3.dist-info/WHEEL
line_profiler_extended-0.0.3.dist-info/RECORD
