Metadata-Version: 2.1
Name: line-profiler-extended
Version: 0.0.3
Summary: Inherits awesome rkern's line-profiler and adds some useful features
Home-page: https://utapyngo.github.io/line-profiler-extended
License: MIT
Author: Ivan Zaikin
Author-email: ut@pyngo.tom.ru
Requires-Python: >=3.7.1,<4.0
Classifier: Development Status :: 4 - Beta
Classifier: Intended Audience :: Developers
Classifier: License :: OSI Approved :: MIT License
Classifier: Operating System :: OS Independent
Classifier: Programming Language :: Python
Classifier: Programming Language :: Python :: 3
Classifier: Programming Language :: Python :: 3.8
Classifier: Programming Language :: Python :: 3.9
Classifier: Programming Language :: Python :: 3.10
Classifier: Programming Language :: Python :: 3.11
Classifier: Programming Language :: Python :: 3
Classifier: Programming Language :: Python :: 3 :: Only
Classifier: Programming Language :: Python :: 3.10
Classifier: Programming Language :: Python :: 3.11
Classifier: Programming Language :: Python :: 3.7
Classifier: Programming Language :: Python :: 3.8
Classifier: Programming Language :: Python :: 3.9
Classifier: Topic :: Software Development :: Libraries
Classifier: Typing :: Typed
Provides-Extra: ipython
Requires-Dist: IPython (>=0.13) ; extra == "ipython"
Requires-Dist: line-profiler (>=4.0,<5.0)
Requires-Dist: pytest (>=5,<8)
Project-URL: Documentation, https://utapyngo.github.io/line-profiler-extended
Project-URL: Repository, https://github.com/utapyngo/line-profiler-extended
